<?xml version="1.0" encoding="UTF-8" ?>
<config>
    <!-- Global Settings -->
    <input-path>hdfs://nameservice1/user/hive/warehouse/tmp.db/api_feature_nor_v1</input-path>
    <output-path>hdfs://nameservice1/tmp/test-hfile-output</output-path>
    <htable-name>fraud_feature_nor_v1</htable-name>
    <field-delimiter>\u0001</field-delimiter>
    <collection-item-delimiter>,</collection-item-delimiter>
    <hbase.zookeeper.quorum>192.168.254.71,192.168.254.72,192.168.254.73</hbase.zookeeper.quorum>
    <hbase.zookeeper.property.clientPort>2181</hbase.zookeeper.property.clientPort>
    <hbase.zookeeper.property.maxClientCnxns>400</hbase.zookeeper.property.maxClientCnxns>
    <hbase.znode.parent>/hbase</hbase.znode.parent>

    <!-- Local Settings -->
    <mapping-info>
       <column-mapping>
            <hive-column-name>imei</hive-column-name>
            <hive-column-type>string</hive-column-type>
            <rowkey>true</rowkey>
        </column-mapping>
        <column-mapping>
            <hive-column-name>value</hive-column-name>
            <hive-column-type>string</hive-column-type>
            <hbase-column-family>A</hbase-column-family>
            <hbase-column-qualifier>black_wifi_cnt</hbase-column-qualifier>
        </column-mapping>
    </mapping-info>

    <mapping-info>
        <partition>
            feature=rent_car_pkg_cnt/data_date=20170430
        </partition>
        <column-mapping>
            <hive-column-name>imei</hive-column-name>
            <hive-column-type>string</hive-column-type>
            <rowkey>true</rowkey>
        </column-mapping>
        <column-mapping>
            <hive-column-name>value</hive-column-name>
            <hive-column-type>string</hive-column-type>
            <hbase-column-family>A</hbase-column-family>
            <hbase-column-qualifier>car_rental_app_usage</hbase-column-qualifier>
        </column-mapping>
    </mapping-info>

    <mapping-info>
        <partition>
            feature=loan_times/data_date=20170430
        </partition>
        <column-mapping>
            <hive-column-name>imei</hive-column-name>
            <hive-column-type>string</hive-column-type>
            <rowkey>true</rowkey>
        </column-mapping>
        <column-mapping>
            <hive-column-name>value</hive-column-name>
            <hive-column-type>string</hive-column-type>
            <hbase-column-family>A</hbase-column-family>
            <hbase-column-qualifier>loan_scale</hbase-column-qualifier>
        </column-mapping>
    </mapping-info>

   <mapping-info>
        <partition>
            feature=price/data_date=20170430
        </partition>
        <column-mapping>
            <hive-column-name>imei</hive-column-name>
            <hive-column-type>string</hive-column-type>
            <rowkey>true</rowkey>
        </column-mapping>
        <column-mapping>
            <hive-column-name>value</hive-column-name>
            <hive-column-type>string</hive-column-type>
            <hbase-column-family>A</hbase-column-family>
            <hbase-column-qualifier>mobile_price</hbase-column-qualifier>
        </column-mapping>
    </mapping-info>

    <mapping-info>
       <column-mapping>
            <hive-column-name>imei</hive-column-name>
            <hive-column-type>string</hive-column-type>
            <rowkey>true</rowkey>
        </column-mapping>
        <column-mapping>
            <hive-column-name>value</hive-column-name>
            <hive-column-type>string</hive-column-type>
            <hbase-column-family>A</hbase-column-family>
            <hbase-column-qualifier>total_app_cnt</hbase-column-qualifier>
        </column-mapping>
    </mapping-info>
</config>
